route_decorator.py
django_route_decorator-0.1.1.dist-info/METADATA
django_route_decorator-0.1.1.dist-info/WHEEL
django_route_decorator-0.1.1.dist-info/top_level.txt
django_route_decorator-0.1.1.dist-info/RECORD
