Metadata-Version: 2.1
Name: django-route-decorator
Version: 0.1.1
Summary: A flask-style `route` decorator for django views
Home-page: https://github.com/imbolc/django-route-decorator
Author: Imbolc
Author-email: imbolc@imbolc.name
License: ISC
Platform: UNKNOWN
Classifier: Development Status :: 4 - Beta
Classifier: Intended Audience :: Developers
Classifier: License :: OSI Approved :: ISC License (ISCL)
Classifier: Programming Language :: Python :: 3
